py_outliers_utils/__init__.py
py_outliers_utils/outliers.py
py_outliers_utils/trim_outliers.py
py_outliers_utils/visualize_outliers.py
py_outliers_utils-1.2.9.dist-info/LICENSE
py_outliers_utils-1.2.9.dist-info/WHEEL
py_outliers_utils-1.2.9.dist-info/METADATA
py_outliers_utils-1.2.9.dist-info/RECORD
