Metadata-Version: 2.1
Name: py-outliers-utils
Version: 1.2.9
Summary: Dealing with outliers
License: MIT
Author: scarlqq
Requires-Python: >=3.9,<4.0
Classifier: License :: OSI Approved :: MIT License
Classifier: Programming Language :: Python :: 3
Classifier: Programming Language :: Python :: 3.10
Classifier: Programming Language :: Python :: 3.9
Requires-Dist: altair (>=4.2.0,<5.0.0)
Requires-Dist: pandas (>=1.4.0,<2.0.0)
